MANIFEST.in
setup.cfg
setup.py
c3pyo/.DS_Store
c3pyo/__init__.py
c3pyo/__init__.pyc
c3pyo/bar_chart.py
c3pyo/bar_chart.pyc
c3pyo/base.py
c3pyo/base.pyc
c3pyo/line_chart.py
c3pyo/line_chart.pyc
c3pyo/pie_chart.py
c3pyo/pie_chart.pyc
c3pyo/scatter_chart.pyc
c3pyo/temp.html
c3pyo/test_base.pyc
c3pyo/utils.py
c3pyo/utils.pyc
c3pyo.egg-info/PKG-INFO
c3pyo.egg-info/SOURCES.txt
c3pyo.egg-info/dependency_links.txt
c3pyo.egg-info/not-zip-safe
c3pyo.egg-info/requires.txt
c3pyo.egg-info/top_level.txt
c3pyo/__pycache__/__init__.cpython-35.pyc
c3pyo/__pycache__/bar_chart.cpython-35.pyc
c3pyo/__pycache__/base.cpython-35.pyc
c3pyo/__pycache__/line_chart.cpython-35.pyc
c3pyo/__pycache__/pie_chart.cpython-35.pyc
c3pyo/__pycache__/utils.cpython-35.pyc
c3pyo/static/.DS_Store
c3pyo/static/c3.css
c3pyo/static/c3.min.js
c3pyo/static/d3.min.js
c3pyo/templates/chart.html