Metadata-Version: 1.0
Name: c3pyo
Version: 0.0.3
Summary: Python C3 - Chart Library for d3.js
Home-page: http://github.com/benalexkeen/C3PyO
Author: Ben Keen
Author-email: bak@benalexkeen.com
License: MIT
Keywords: plot, graph, c3, d3,data,visualization
Platform: UNKNOWN
